drivy_tools/__init__.py
drivy_tools/config.py
drivy_tools/main.py
drivy_tools/src/__init__.py
drivy_tools/src/client.py
drivy_tools/src/drivy_api.py
drivy_tools/src/enums.py
drivy_tools/src/models.py
drivy_tools/src/parsing.py
drivy_tools/src/utils/__init__.py
drivy_tools/src/utils/config_utils.py
drivy_tools/src/utils/fetch_utils.py
drivy_tools/src/utils/various_utils.py
drivy_tools/state.py
drivy_tools-0.3.2.dist-info/entry_points.txt
drivy_tools-0.3.2.dist-info/WHEEL
drivy_tools-0.3.2.dist-info/METADATA
drivy_tools-0.3.2.dist-info/RECORD
