Metadata-Version: 2.1
Name: drivy-tools
Version: 0.3.2
Summary: Tool to make use of Drivy
Home-page: https://github.com/zekiblue/drivy_tools
License: Proprietary
Author: zekiblue
Author-email: zekiberkulu@gmail.com
Requires-Python: >=3.9,<4.0
Classifier: License :: Other/Proprietary License
Classifier: Programming Language :: Python :: 3
Classifier: Programming Language :: Python :: 3.10
Classifier: Programming Language :: Python :: 3.9
Requires-Dist: httpx (>=0.19.0,<0.20.0)
Requires-Dist: pydantic (>=1.8.2,<2.0.0)
Requires-Dist: tqdm (>=4.62.3,<5.0.0)
Requires-Dist: typer (>=0.4.0,<0.5.0)
Requires-Dist: user_agent (>=0.1.9,<0.2.0)
Project-URL: Repository, https://github.com/zekiblue/drivy_tools
